pyflow/__init__.py
pyflow/graph_builder.py
pyflow/graph_document.py
pyflow/utils.py
pyflow/node/__init__.py
pyflow/node/base_node.py
pyflow/node/data_holder_node.py
pyflow/node/data_node.py
pyflow/node/operation_node.py
pyflow_viz-0.43.dist-info/LICENSE
pyflow_viz-0.43.dist-info/METADATA
pyflow_viz-0.43.dist-info/WHEEL
pyflow_viz-0.43.dist-info/top_level.txt
pyflow_viz-0.43.dist-info/RECORD
