Metadata-Version: 2.1
Name: pyflow-viz
Version: 0.43
Summary: Lazy computation directed acyclic graph builder
Home-page: https://github.com/mozjay0619/pyflow-viz
Author: Jay Kim
Author-email: mozjay0619@gmail.com
License: DSB 3-clause
Platform: UNKNOWN
Requires-Python: >=3
License-File: LICENSE
Requires-Dist: numpy (>=1.18.2)
Requires-Dist: pandas (>=0.25.3)
